{"@context":"https://worksets.htrc.illinois.edu/context/ef_context.jsonld","schemaVersion":"https://schemas.hathitrust.org/EF_Schema_v_3.0","id":"https://data.analytics.hathitrust.org/extracted-features/20200210/uiuo.ark:/13960/t7fr63p38","htid":"uiuo.ark:/13960/t7fr63p38","type":"DataFeed","publisher":{"id":"https://analytics.hathitrust.org","type":"Organization","name":"HathiTrust Research Center"},"datePublished":20200210,"metadata":{"schemaVersion":"https://schemas.hathitrust.org/EF_Schema_MetadataSubSchema_v_3.0","id":"http://hdl.handle.net/2027/uiuo.ark:/13960/t7fr63p38","type":["DataFeedItem","Book"],"dateCreated":20200209,"title":"Commerce with Central and South America and with the Orient, showing the need of reciprocity, direct lines of transportation and the Nicaragua canal : speech -- before the Home Market Club -- Boston, November 21, 1895.","contributor":[{"id":"http://www.viaf.org/viaf/68516366","type":"http://id.loc.gov/ontologies/bibframe/Person","name":"Miller, Warner, 1838-1918."},{"id":"http://www.viaf.org/viaf/151560497","type":"http://id.loc.gov/ontologies/bibframe/Organization","name":"Home Market Club (Boston)"}],"pubDate":1896,"publisher":{"id":"http://catalogdata.library.illinois.edu/lod/entities/ProvisionActivityAgent/ht/Home%20Market%20Club","type":"http://id.loc.gov/ontologies/bibframe/Organization","name":"Home Market Club"},"pubPlace":{"id":"http://id.loc.gov/vocabulary/countries/mau","type":"http://id.loc.gov/ontologies/bibframe/Place","name":"Massachusetts"},"language":"eng","accessRights":"pd","accessProfile":"open","sourceInstitution":{"type":"http://id.loc.gov/ontologies/bibframe/Organization","name":"IUIUC"},"mainEntityOfPage":["https://catalog.hathitrust.org/Record/102200291","http://catalog.hathitrust.org/api/volumes/brief/oclc/77328678.json","http://catalog.hathitrust.org/api/volumes/full/oclc/77328678.json"],"oclc":"77328678","genre":"http://id.loc.gov/vocabulary/marcgt/doc","typeOfResource":"http://id.loc.gov/ontologies/bibframe/Text","lastRightsUpdateDate":20180315},"features":{"schemaVersion":"https://schemas.hathitrust.org/EF_Schema_FeaturesSubSchema_v_3.0","id":"http://hdl.handle.net/2027/uiuo.ark:/13960/t7fr63p38","type":"DataFeedItem","dateCreated":20200124,"pageCount":8,"pages":[{"seq":"00000001","version":"1dc97f5d32b87a974d7908aa3d3c5c4f","tokenCount":64,"lineCount":22,"emptyLineCount":9,"sentenceCount":3,"header":null,"body":{"tokenCount":64,"lineCount":22,"emptyLineCount":9,"sentenceCount":3,"capAlphaSeq":2,"beginCharCount":{"T":1,"A":1,"I":1,"i":1,"B":2,"P":1,"C":2,"H":1,"O":2,"S":1},"endCharCount":{"E":1,".":3,"A":1,",":2,"G":1,"H":1,"K":1,":":1,"R":1,"S":1},"tokenPosCount":{"IN":{"IN":1},"SPEECH":{"NN":1},"WITH":{"IN":2},"iSK":{"NNP":1},"SHOWING":{"VBG":1},"CLUB":{"NN":1},".":{".":3},"ANp":{"NNP":1},"MILLER":{"NNP":1},"ORIENT":{"NNP":1},"Published":{"VBN":1},"THE":{"DT":4},"HOME":{"NNP":1},"BEFORE":{"IN":1},"SOUTH":{"NNP":1},"HALL":{"NNP":1},"OF":{"IN":3},"21":{"CD":1},"RECIPROCITY":{"NNP":1},"MUSIC":{"NNP":1},"Market":{"NNP":1},"Home":{"NNP":1},"NICARAGUA":{"NNP":1},",":{",":8},"BOSTON":{"NNP":2},"LINES":{"NNPS":1},"COMMERCE":{"NNP":1},"1895":{"CD":1},"NEW":{"NNP":1},"CENTRAL":{"NNPS":1},"1S9G":{"NNP":1},"CANAL":{"NNP":1},"by":{"IN":1},"NOVEMBER":{"NNP":1},"OE":{"NN":1},"Hon.":{"NNP":1},"AMERICA":{"NNP":1},"NEED":{"NNS":1},"MARKET":{"NNP":1},":":{":":1},"TRANSPORTATION":{"NNP":1},"AND":{"CC":2},"DIRECT":{"NNP":1},"Club":{"NNP":1},"YORK":{"NNP":1},"the":{"DT":1},"WARNER":{"NNP":1}}},"footer":null,"calculatedLanguage":"en"},{"seq":"00000002","version":"0007b25260e52c7dee586df20ae32121","tokenCount":354,"lineCount":37,"emptyLineCount":4,"sentenceCount":8,"header":null,"body":{"tokenCount":354,"lineCount":37,"emptyLineCount":4,"sentenceCount":8,"capAlphaSeq":2,"beginCharCount":{"e":3,"s":2,"n":3,"T":1,"t":2,"f":1,"A":1,"a":2,"m":1,"M":1,"b":3,"l":1,"p":4,"c":1,"W":1,"w":1,"k":2,"o":2,"S":1},"endCharCount":{"e":9,"s":1,".":2,"]":1,"y":1,"t":1,"f":2,"-":10,",":1,"—":1,"r":2,"d":2},"tokenPosCount":{"compete":{"VB":1},"able":{"JJ":1},"for":{"IN":4},"Representatives":{"NNPS":1},"find":{"VB":1},"business":{"NN":2},"SPEECH":{"NN":1},"produce":{"VB":1},"people":{"NNS":1},"unhesitatingly":{"RB":1},"any":{"DT":1},"production":{"NN":1},"successfully":{"RB":1},"years":{"NNS":1},"in":{"IN":6},"With":{"IN":1},"have":{"VBP":2},"are":{"VBP":2},"is":{"VBZ":1},"improvement":{"NN":1},"manufactures":{"VBZ":1},"forerunner":{"NN":1},"elections":{"NNS":1},"prices":{"NNS":1},"market":{"NN":3},".":{".":7},"standard":{"NN":1},"In":{"IN":1},"but":{"CC":2},"nation":{"NN":1},"President":{"NNP":2},"MILLER":{"NNP":1},"industries":{"NNS":1},"suddenly":{"RB":1},"checked":{"VBN":1},"return":{"NN":2},"THE":{"DT":1},"own":{"JJ":1},"up":{"RB":1},"seek":{"VB":1},"so":{"RB":1},"our":{"PRP$":8},"do":{"VB":1},"all":{"PDT":1,"DT":3},"election":{"NN":1},"look":{"VB":1},"advanced":{"VBD":1},"prepare":{"VB":1},"necessary":{"JJ":1},"every":{"DT":1},"Allow":{"VB":1},"exceeds":{"VBZ":1},"steel":{"NN":1},"transportation":{"NN":1},"certainty":{"NN":1},"two":{"CD":1},"a":{"DT":8},"meat":{"NN":1},"manufacture":{"NN":1},"prosperity":{"NN":2},"forward":{"RB":1},"as":{"IN":1},"implements":{"VBZ":1},"nearly":{"RB":1},"-LSB-":{"-LRB-":1},"year":{"NN":1},"Senate":{"NNP":1},"We":{"PRP":2},"Mr.":{"NNP":1},"especially":{"RB":1},"quite":{"RB":1},"dreamed":{"VBN":1},"re-employment":{"NN":1},"products":{"NNS":3},"or":{"CC":1},"confidently":{"RB":1},"confidence":{"NN":1},"OF":{"IN":1},"Applause":{"NN":1},"others":{"NNS":1},"such":{"JJ":1},"building":{"NN":1},"increased":{"VBN":3},"that":{"IN":1},"Market":{"NNP":1},"numbers":{"NNS":1},"to":{"TO":7},"existing":{"VBG":1},"Home":{"NNP":1},"Gentlemen":{"NNP":1},"now":{"RB":2},"you":{"PRP":1},"agriculture":{"NN":2},"railroad":{"NN":1},"department":{"NN":1},",":{",":21},"home":{"NN":1},";":{":":5},"was":{"VBD":1},"surplus":{"NN":2},"Republican":{"JJ":1,"NNP":2},"wheat":{"NN":2},"at":{"IN":1},"profitable":{"JJ":2},"The":{"DT":1},"dollars":{"NNS":1},"over":{"IN":1},"can":{"MD":3},"on":{"IN":5},"kinds":{"NNS":1},"equal":{"JJ":1},"iron":{"NN":1},"grades":{"NNS":1},"assured":{"VBN":1},"necessitate":{"VB":1},"wages":{"NNS":1},"me":{"PRP":1},"supply":{"VB":1},"mining":{"NN":1},"by":{"IN":2},"cottons":{"NNS":1},"goods":{"NNS":1},"agricultural":{"JJ":2},"majority":{"NN":1},"few":{"JJ":1},"laborers":{"NNS":1},"machinery":{"NN":1},"foreign":{"JJ":1},"-RSB-":{"-RRB-":1},"not":{"RB":1},"manufacturing":{"NN":1},"with":{"IN":1},"necessity":{"NN":1},"principal":{"JJ":1},"next":{"JJ":1},"give":{"VBP":1},"resources":{"NNS":1},"leading":{"VBG":1},"which":{"WDT":5},"employment":{"NN":1},"congratulate":{"VB":1},"an":{"DT":3},"shores":{"NNS":1},"era":{"NN":1},"natural":{"JJ":1},"development":{"NN":1},"be":{"VB":1},"supplies":{"NNS":1},"large":{"JJ":2},"1892":{"CD":2},"million":{"CD":1},"power":{"NN":1},"more":{"RBR":1},"output":{"NN":1},"necessities":{"NNS":1},"annually":{"RB":1},"greater":{"JJR":1},"--":{":":1},"activity":{"NN":1},"House":{"NNP":1},"many":{"JJ":4},"lines":{"NNS":2},"demand":{"NN":1},"we":{"PRP":5},"past":{"JJ":1},"value":{"NN":1},"limits":{"NNS":1},"cotton":{"NN":2},"HON.":{"NNP":1},"known":{"VBN":1},"possible":{"JJ":1},"may":{"MD":2},"other":{"JJ":2},"of":{"IN":30},"and":{"CC":14},"period":{"NN":1},"Club":{"NNP":1},"beyond":{"IN":1},"compelled":{"VBN":1},"the":{"DT":20},"never":{"RB":1},"WARNER":{"NNP":1},"only":{"RB":2}}},"footer":null,"calculatedLanguage":"en"},{"seq":"00000003","version":"b3495743a4f03369777b63c01a200ed7","tokenCount":491,"lineCount":63,"emptyLineCount":13,"sentenceCount":18,"header":null,"body":{"tokenCount":491,"lineCount":63,"emptyLineCount":13,"sentenceCount":18,"capAlphaSeq":3,"beginCharCount":{"E":1,"s":2,"n":1,"T":1,"t":9,"<":1,"f":2,"a":5,"m":1,"M":1,"I":1,"b":2,"g":2,"p":2,"0":1,"W":1,"h":1,"r":4,"w":4,"3":1,"O":1,"o":4,"z":1,"S":1},"endCharCount":{"e":12,"s":3,"n":2,".":3,"]":1,"y":2,"t":2,"f":1,"a":1,"-":10,";":1,"1":1,"h":2,"r":2,"3":1,"o":4,"d":2},"tokenPosCount":{"wise":{"JJ":1},"covet":{"VB":1},"dissimilar":{"JJ":1},"for":{"IN":8},"s":{"NNS":1},"find":{"VBP":1},"produce":{"VB":1},"cereals":{"NNS":1},"people":{"NNS":3},"dye":{"VB":1},"any":{"DT":1},"wars":{"NNS":1},"Nature":{"NNP":1},"this":{"DT":1},"portions":{"NNS":1},"in":{"IN":5},"have":{"VB":1,"VBP":5},"fierce":{"JJ":1},"success":{"NN":1},"are":{"VBP":4},"conquest":{"NN":1},"is":{"VBZ":1},"northern":{"JJ":1},"require":{"VBP":1},"cultivate":{"VBP":1},"South":{"NNP":4},"manufactures":{"VBZ":1},"market":{"NN":1},"hides":{"VBZ":1},"They":{"PRP":1},"latitudes":{"NNS":1},"sugar":{"NN":1},".":{".":17},"monopoly":{"NN":1},"In":{"IN":1},"but":{"CC":3},"nation":{"NN":1},"whether":{"IN":1},"materials":{"NNS":1},"unable":{"JJ":1},"abroad":{"RB":1},"industries":{"NNS":1},"elsewhere":{"RB":1},"sea":{"NN":1},"Britain":{"NNP":1},"profit":{"NN":1},"if":{"IN":2},"world":{"NN":2},"own":{"JJ":2},"seek":{"VB":1},"population":{"NN":1},"so":{"RB":1},"our":{"PRP$":9},"must":{"MD":1},"friendship":{"NN":1},"subdue":{"VBP":1},"all":{"PDT":1,"DT":1},"<":{"JJR":1},"accumulation":{"NN":1},"present":{"JJ":1},"look":{"VBP":1},"neighbors":{"NNS":2},"mahogany":{"NN":1},"confined":{"VBD":1},"every":{"DT":1},"doors":{"NNS":1},"set":{"VBN":1},"outside":{"JJ":1},"glory":{"NN":1},"Great":{"JJ":1},"1,000":{"CD":1},"us":{"PRP":2},"it":{"PRP":1},"lying":{"VBG":1},"70,000,000":{"CD":1},"spectators":{"NNS":1},"two":{"CD":1},"closer":{"JJR":1},"a":{"DT":6},"Mexico":{"NNP":2},"barbarous":{"JJ":2},"meat":{"NN":1},"manufacture":{"NN":1},"domains":{"NNS":1},"prosperity":{"NN":1},"though":{"IN":1},"as":{"IN":1,"RB":1},"nearly":{"RB":1},"5":{"CD":1},"has":{"VBZ":1},"-LSB-":{"-LRB-":1},"We":{"PRP":4},"trade":{"NN":5},"temperate":{"JJ":2},"Exchange":{"NNP":1},"Europe":{"NNP":2},"products":{"NNS":3},"or":{"CC":2},"seems":{"VBZ":1},"Indies":{"NNP":2},"scramble":{"NN":1},"Applause":{"NN":1},"come":{"VB":1},"such":{"JJ":3},"they":{"PRP":5},"extend":{"VB":1},"belonging":{"VBG":1},"outlet":{"NN":1},"statesmanship":{"NN":1},"that":{"IN":3},"contest":{"NN":1},"amount":{"NN":1},"continent":{"NN":1},"producing":{"VBG":2},"blessings":{"NNS":1},"to":{"TO":11},"Today":{"NN":1},"uncivilized":{"JJ":1},"-":{":":2},",":{",":35},"woods":{"NNS":1},"most":{"RBS":1},"these":{"DT":2},"wares":{"NNS":1},";":{":":2},"surplus":{"NN":1},"hold":{"VB":2},"found":{"VBN":1},"countries":{"NNS":1},"000,000":{"CD":1},"at":{"IN":1},"1":{"CD":1},"profitable":{"JJ":1},"The":{"DT":3},"older":{"JJR":1},"over":{"IN":1},"need":{"VBP":1},"on":{"IN":2},"globe":{"NN":2},"wants":{"VBZ":2},"raw":{"JJ":3},"heretofore":{"RB":1},"therefore":{"RB":1},"take":{"VB":2},"engaged":{"VBN":1},"everything":{"NN":1},"supply":{"VB":1},"them":{"PRP":2},"by":{"IN":3},"coffee":{"NN":1},"will":{"MD":3},"much":{"JJ":1},"little":{"RB":1},"while":{"IN":1},"their":{"PRP$":7},"feed":{"VB":1},"-RSB-":{"-RRB-":1},"not":{"RB":3},"with":{"IN":5},"wealth":{"NN":1},"hemispheres":{"NNS":1},"0":{"CD":1},"necessity":{"NN":1},"give":{"VB":2},"hemp":{"NN":1},"energies":{"NNS":1},"relations":{"NNS":2},"resources":{"NNS":1},"both":{"DT":1},"workshops":{"NNS":1},"nature":{"NN":1},"use":{"NN":1},"make":{"VBP":1},"which":{"WDT":2},"requires":{"VBZ":1},"an":{"DT":1},"hot":{"JJ":1},"termed":{"VBN":1},"natural":{"JJ":1},"development":{"NN":2},"possessions":{"NNS":1},"thrive":{"VBP":1},"large":{"JJ":1},"nations":{"NNS":3},"Orient":{"NNP":1},"France":{"NNP":1},"returning":{"VBG":1},"United":{"NNP":1},"themselves":{"PRP":1},"prompted":{"VBN":1},"possess":{"VB":1},"stood":{"VBN":1},"America":{"NNP":4},"Pacific":{"NNP":1},"power":{"NN":1},"European":{"JJ":1},"Central":{"NNP":2},"Manufactures":{"VBZ":1},"civilization":{"NN":1},"between":{"IN":2},"compel":{"VB":1},"West":{"NNP":2},"etc.":{"FW":1},"$":{"$":1},"zn":{"VBP":1},"3":{"CD":1},"made":{"VBN":1},"Africa":{"NNP":2},"possession":{"NN":1},"we":{"PRP":3},"civilized":{"JJ":1},"zone":{"NN":2},"military":{"JJ":1},"limits":{"NNS":1},"cotton":{"NN":1},"devoted":{"VBN":1},"great":{"JJ":1},"islands":{"NNS":1},"possible":{"JJ":1},"may":{"MD":2},"tropics":{"NNS":1},"States":{"NNPS":1},"of":{"IN":26},"Germany":{"NNP":1},"and":{"CC":17},"Southern":{"NNP":1},"increase":{"NN":1},"desire":{"NN":1},"o":{"NN":4},"beyond":{"IN":1},"the":{"DT":37},"North":{"NNP":2},"uninterested":{"JJ":1},"only":{"RB":1}}},"footer":null,"calculatedLanguage":"en"},{"seq":"00000004","version":"41c011d6e97ed23a4a6916c832225a66","tokenCount":483,"lineCount":51,"emptyLineCount":9,"sentenceCount":20,"header":null,"body":{"tokenCount":483,"lineCount":51,"emptyLineCount":9,"sentenceCount":20,"capAlphaSeq":2,"beginCharCount":{"E":1,"s":1,"4":1,"n":2,"y":1,"T":4,"t":3,"u":1,"U":1,"f":3,"A":1,"I":1,"i":1,"L":1,"[":1,"p":2,"0":3,"2":1,"C":1,"c":1,"h":3,"w":3,"$":4,"o":1},"endCharCount":{"e":7,"4":1,"n":1,".":7,"]":1,"y":1,"t":1,"f":3,"-":9,",":2,"—":1,"?":1,"h":1,"r":2,"k":1,"o":1,"d":2},"tokenPosCount":{"Much":{"JJ":1},"for":{"IN":2},"neighbor":{"NN":1},"construction":{"NN":1},"justified":{"VBN":1},"railroads":{"NNS":1},"lead":{"VBP":1},"9,769,000":{"CD":1},"chiefly":{"RB":1},"years":{"NNS":2},"1893":{"CD":1},"this":{"DT":2},"in":{"IN":9},"With":{"IN":1},"87,000,000":{"CD":2},"have":{"VBP":4},"are":{"VBP":1},"is":{"VBZ":1},"100,000,000":{"CD":1},"South":{"NNP":2},"manufactures":{"VBZ":1},"seen":{"VBN":1},"4":{"CD":1},"All":{"PDT":1},"furnish":{"VB":1},"bulk":{"NN":1},"nearest":{"JJS":1},"348,000,000":{"CD":1},".":{".":18},"90":{"CD":1},"would":{"MD":1},"400,000,000":{"CD":1},"awaiting":{"VBG":1},"pleasure":{"NN":1},"33":{"CD":2},"return":{"NN":1},"profit":{"NN":2},"world":{"NN":1},"Trade":{"NNP":1},"During":{"IN":1},"deeply":{"RB":1},"Why":{"WRB":1},"our":{"PRP$":9},"per":{"IN":8},"78,000,000":{"CD":1},"vast":{"JJ":1},"appear":{"VB":1},"22":{"CD":1},"all":{"PDT":1},"Let":{"VB":1},"30,000,000":{"CD":2},"figures":{"NNS":2},"look":{"VB":1},"International":{"NNP":1},"55,000":{"CD":1},"doors":{"NNS":1},"us":{"PRP":1},"it":{"PRP":3},"Direct":{"JJ":1},"two":{"CD":1},"Ours":{"NNP":1},"entire":{"JJ":3},"a":{"DT":2},"Mexico":{"NNP":2},"21,000,000":{"CD":1},"exports":{"NNS":2},"because":{"IN":1},"exported":{"VBD":4},"nearly":{"RB":1},"has":{"VBZ":2},"she":{"PRP":1},"-LSB-":{"-LRB-":2},"year":{"NN":6},"proportionate":{"JJ":1},"456,000,000":{"CD":1},"We":{"PRP":1},"trade":{"NN":5},"products":{"NNS":10},"or":{"CC":8},"These":{"DT":2},"English":{"NNP":1},"interested":{"JJ":1},"Applause":{"NN":2},"76":{"CD":1},"Value":{"NN":1},"leaving":{"VBG":1},"increased":{"VBN":1},"that":{"IN":2,"WDT":1},"amount":{"NN":3},"to":{"TO":9},"direct":{"JJ":1},"took":{"VBD":4},"-":{":":3},"Lines":{"NNS":1},"Transportation":{"NN":1},"importations":{"NNS":1},",":{",":33},"share":{"NN":1},"these":{"DT":2},";":{":":1},"countries":{"NNS":1},"000,000":{"CD":1},"taken":{"VBN":1},"79,000,000":{"CD":1},"at":{"IN":2},"through":{"IN":1},"The":{"DT":2},"need":{"VBP":1},"Countries":{"NNP":1},"on":{"IN":1},"same":{"JJ":6},"25":{"CD":1},"60":{"CD":1},"lies":{"VBZ":1},"worth":{"NN":1},"47":{"CD":1},"take":{"VB":1,"VBP":1},"imported":{"VBN":3,"VBD":1},"Cuba":{"NNP":3},"food":{"NN":1},"them":{"PRP":2},"demanding":{"VBG":1},"should":{"MD":2},"will":{"MD":1},"few":{"JJ":1},"while":{"IN":1},"their":{"PRP$":1},"-RSB-":{"-RRB-":1},"moment":{"NN":1},"not":{"RB":3},"with":{"IN":4},"from":{"IN":5},"?":{".":1},"controlled":{"VBN":1},"000":{"CD":2},"both":{"DT":1},"furnished":{"VBD":4},"sent":{"VBN":1},"permitted":{"VBN":1},"whole":{"JJ":1},"It":{"PRP":4},"which":{"WDT":10},"control":{"VB":1},"five":{"CD":1},"be":{"VB":3},"large":{"JJ":2},"into":{"IN":1},"United":{"NNP":7},"her":{"PRP$":7},"Need":{"NN":1},"rapidly":{"RB":1},"Central":{"NNP":2},"directly":{"RB":1},"gone":{"VBN":1},"--":{":":2},"American":{"NNP":2},"many":{"JJ":1},"$":{"$":18},"made":{"VBN":1},"during":{"IN":2},"vessels":{"NNS":1},"very":{"RB":1},"we":{"PRP":7},"18,000":{"CD":1},"past":{"JJ":2,"NN":1},"magnitude":{"NN":1},"value":{"NN":2},"possible":{"JJ":1},"33,000,000":{"CD":1},"owing":{"VBG":1},"States":{"NNPS":11},"might":{"MD":1},"of":{"IN":26},"and":{"CC":6},"14,000,000":{"CD":1},"carry":{"VB":1},"product":{"NN":1},"5,125,000":{"CD":1},"the":{"DT":28},"cent":{"NN":8},"those":{"DT":1},"only":{"RB":2}}},"footer":null,"calculatedLanguage":"en"},{"seq":"00000005","version":"e0b97439b14ff05d6dda42251aa084ff","tokenCount":440,"lineCount":50,"emptyLineCount":8,"sentenceCount":17,"header":null,"body":{"tokenCount":440,"lineCount":50,"emptyLineCount":8,"sentenceCount":17,"capAlphaSeq":4,"beginCharCount":{"e":1,"s":2,"T":3,"Y":2,"t":8,"u":1,"a":2,"5":1,"m":1,"I":2,"i":4,"L":1,"b":1,"B":1,"l":2,"p":1,"c":3,"W":1,"h":2,"w":1,"o":1,"S":1},"endCharCount":{"e":3,"s":5,".":4,"]":2,"t":1,"f":2,"5":1,"m":1,"-":10,",":1,"p":1,"h":1,"r":1,"w":2,"o":3,"d":4},"tokenPosCount":{"Janeiro":{"NNP":1},"enable":{"VB":2},"entirely":{"RB":1},"failure":{"NN":1},"business":{"NN":2},"people":{"NNS":1},"reach":{"VB":1},"series":{"NN":1},"due":{"JJ":1},"largely":{"RB":1},"any":{"DT":1},"managed":{"VBN":1},"portion":{"NN":1},"chiefly":{"RB":1},"this":{"DT":2},"instead":{"RB":1},"in":{"IN":6},"treaties":{"NNS":1},"have":{"VBP":1},"cargo":{"NN":1},"fair":{"JJ":1},"is":{"VBZ":7},"communication":{"NN":2},"South":{"NNP":4},"manufactures":{"VBZ":2},"manufactured":{"JJ":1},"freighted":{"VBN":1},"cheap":{"JJ":1},"hands":{"NNS":1},"furnish":{"VB":1},"carried":{"VBN":1},"commission":{"NN":1},"This":{"DT":5},".":{".":16},"In":{"IN":1},"but":{"CC":1},"Reciprocity":{"NN":1},"different":{"JJ":1},"would":{"MD":1},"giving":{"VBG":1},"substantially":{"RB":1},"return":{"NN":1},"securing":{"VBG":1},"so":{"RB":2},"clear":{"JJ":1},"our":{"PRP$":7},"must":{"MD":1},"do":{"VBP":1},"all":{"DT":3,"PDT":1},"necessary":{"JJ":1},"us":{"PRP":6},"it":{"PRP":3},"lying":{"VBG":1},"trip":{"NN":1},"Administration":{"NNP":1},"a":{"DT":4},"establish":{"VB":1},"as":{"IN":1},"ports":{"NNS":3},"nearly":{"RB":1},"5":{"CD":1},"regular":{"JJ":3},"-LSB-":{"-LRB-":3},"We":{"PRP":1},"trade":{"NN":5},"coming":{"VBG":1},"triangular":{"JJ":1},"products":{"NNS":8},"or":{"CC":2},"advantage":{"NN":1},"There":{"EX":1},"English":{"JJ":1,"NNP":2},"Applause":{"NN":3},"last":{"JJ":1},"bottoms":{"NNS":1},"that":{"IN":6},"well-established":{"JJ":1},"Defeat":{"NN":1},"sending":{"VBG":1},"possibility":{"NN":1},"to":{"TO":15},"factor":{"NN":1},"exchange":{"NN":1},"Our":{"PRP$":1},"fact":{"NN":2},"returned":{"VBD":1},",":{",":16},"share":{"NN":1},"considerable":{"JJ":1},";":{":":1},"making":{"VBG":1},"was":{"VBD":3},"there":{"EX":3,"RB":1},"hold":{"VB":1},"countries":{"NNS":4},"Republican":{"NNP":1},"desirable":{"JJ":1},"taken":{"VBN":1},"experience":{"NN":1},"79,000,000":{"CD":1},"at":{"IN":1},"through":{"IN":2},"profitable":{"JJ":1},"The":{"DT":3},"Brazil":{"NNP":4},"illustration":{"NN":1},"go":{"VB":1},"marine":{"NN":1},"markets":{"NNS":3},"can":{"MD":1},"same":{"JJ":1},"shown":{"VBN":1},"raw":{"JJ":2},"worth":{"NN":1},"reciprocity":{"NN":1},"take":{"VB":2},"ship":{"NN":1},"engaged":{"VBD":1},"itself":{"PRP":1},"territory":{"NN":1},"York":{"NNP":2},"establishment":{"NN":1},"If":{"IN":1},"order":{"NN":1},"mail":{"NN":1},"commercial":{"JJ":1},"by":{"IN":2},"he":{"PRP":1},"coffee":{"NN":2},"back":{"RP":1},"their":{"PRP$":1},"unless":{"IN":1},"developed":{"VBD":1},"-RSB-":{"-RRB-":3},"not":{"RB":1},"with":{"IN":4},"from":{"IN":4},"person":{"NN":1},"give":{"VB":2},"taking":{"VBG":1},"first":{"JJ":1,"RB":3},"Rio":{"NNP":1},"sail":{"NN":1},"Establishment":{"NN":1},"bring":{"VB":2},"steamship":{"NN":2},"put":{"VB":1,"VBD":1},"leading":{"VBG":1},"its":{"PRP$":1},"which":{"WDT":2},"shall":{"MD":1},"almost":{"RB":1},"an":{"DT":1},"be":{"VB":2},"large":{"JJ":1},"into":{"IN":4},"nations":{"NNS":1},"United":{"NNP":1},"her":{"PRP$":5},"time":{"NN":1},"America":{"NNP":2},"Liverpool":{"NNP":2},"Central":{"NNP":2},"manufacturer":{"NN":1},"New":{"NNP":2},"directly":{"RB":1},"recommended":{"VBD":1},"merchant":{"NN":2},"between":{"IN":2},"compel":{"VB":1},"steamers":{"NNS":1},"develop":{"VBP":1},"1894":{"CD":1},"American":{"JJ":2,"NNP":1},"except":{"IN":1},"lines":{"NNS":3},"$":{"$":2},"made":{"VBN":1},"no":{"DT":4},"vessels":{"NNS":1},"very":{"RB":1},"we":{"PRP":4},"having":{"VBG":1},"proposition":{"NN":1},"argument":{"NN":1},"needs":{"VBZ":1},"England":{"NNP":2},"value":{"NN":1},"policy":{"NN":1},"thereby":{"RB":1},"practice":{"NN":1},"may":{"MD":1},"secure":{"VB":1},"States":{"NNPS":1},"of":{"IN":24},"and":{"CC":16},"today":{"NN":1},"intercommunication":{"NN":1},"rapid":{"JJ":3},"14,000,000":{"CD":1},"acceptance":{"NN":1},"the":{"DT":18},"those":{"DT":2},"only":{"RB":1}}},"footer":null,"calculatedLanguage":"en"},{"seq":"00000006","version":"c53438345793daa710520a080918fa15","tokenCount":451,"lineCount":48,"emptyLineCount":5,"sentenceCount":11,"header":null,"body":{"tokenCount":451,"lineCount":48,"emptyLineCount":5,"sentenceCount":11,"capAlphaSeq":4,"beginCharCount":{"s":5,"n":1,"T":1,"t":8,"u":1,"U":1,"A":2,"a":2,"m":2,"i":1,"6":1,"b":2,"[":1,"p":4,"C":1,"c":4,"h":1,"w":1,"o":3,"d":1},"endCharCount":{"e":2,"s":4,"n":3,".":3,"]":1,"y":4,"t":3,"f":1,"-":8,",":3,"6":1,"g":1,"l":1,"c":1,"r":2,"d":5},"tokenPosCount":{"for":{"IN":2},"negotiated":{"VBN":3},"conditions":{"NNS":1},"duty":{"NN":2},"further":{"JJ":1},"people":{"NNS":5},"justified":{"VBN":1},"prove":{"VB":1},"successfully":{"RB":1},"Department":{"NNP":1},"this":{"DT":5},"instead":{"RB":1},"in":{"IN":10},"regard":{"VB":1},"treaties":{"NNS":4},"have":{"VBP":1},"your":{"PRP$":1},"once":{"RB":1},"manner":{"NN":1},"are":{"VBP":1},"is":{"VBZ":1},"wisest":{"JJS":1},"South":{"NNP":3},"All":{"PDT":1},"Washington":{"NNP":1},"than":{"IN":1},"familiar":{"JJ":1},"Democratic":{"JJ":2},"late":{"JJ":1},"Administra":{"NNP":1},"careful":{"JJ":1},".":{".":10},"but":{"CC":2},"whether":{"IN":1},"undertake":{"VB":1},"would":{"MD":1},"proper":{"JJ":1},"return":{"NN":1},"if":{"IN":1},"scant":{"JJ":1},"own":{"JJ":3},"up":{"RP":1},"so":{"IN":1,"RB":3},"our":{"PRP$":9},"led":{"VBD":1},"all":{"PDT":5},"undertaken":{"VBN":1},"Admitted":{"VBN":1},"previous":{"JJ":1},"had":{"VBD":3},"present":{"JJ":1},"diplomatic":{"JJ":1},"Certainly":{"RB":1},"neighbors":{"NNS":1},"result":{"NN":1},"held":{"VBN":1},"undoubtedly":{"RB":1},"abrogation":{"NN":1},"Pan-American":{"JJ":1},"Great":{"JJ":1},"us":{"PRP":2},"it":{"PRP":2},"Congress":{"NNP":1},"efforts":{"NNS":1},"commerce":{"NN":1},"failed":{"VBN":1},"closer":{"JJR":1},"a":{"DT":4},"establish":{"VB":1},"receive":{"VB":1},"attention":{"NN":1},"accomplished":{"VBN":1},"conclusively":{"RB":1},"exports":{"NNS":1},"ports":{"NNS":1},"persistent":{"JJ":1},"opposition":{"NN":1},"-LSB-":{"-LRB-":1},"year":{"NN":2},"trade":{"NN":1},"adoption":{"NN":1},"lower":{"JJR":1},"products":{"NNS":2},"or":{"CC":1},"country":{"NN":3},"refusing":{"VBG":1},"There":{"EX":1},"mails":{"NNS":1},"applause":{"NN":1},"such":{"JJ":1},"they":{"PRP":4},"I":{"PRP":1},"statesmanship":{"NN":1},"negotiations":{"NNS":1},"that":{"IN":6,"WDT":1,"DT":1},"acccorded":{"VBN":1},"to":{"TO":12},"instrumentality":{"NN":1},"-":{":":1},"you":{"PRP":1},"did":{"VBD":2},",":{",":21},"greatly":{"RB":1},"most":{"RBS":2},"these":{"DT":1},";":{":":1},"was":{"VBD":5},"change":{"NN":1},"6":{"CD":1},"countries":{"NNS":3},"at":{"IN":2},"through":{"IN":1},"been":{"VBN":1},"The":{"DT":4},"injured":{"VBN":1},"go":{"VB":1},"destroy":{"VB":1},"results":{"NNS":1},"can":{"MD":1},"on":{"IN":1},"being":{"VBG":1},"wants":{"VBZ":1},"ground":{"NN":1},"raw":{"JJ":1},"after":{"IN":1},"party":{"NN":2},"carrying":{"VBG":1},"reciprocity":{"NN":4},"take":{"VB":1},"everything":{"NN":1},"Unfortunately":{"RB":1},"them":{"PRP":1},"acted":{"VBD":1},"by":{"IN":2},"returns":{"NNS":1},"either":{"CC":1},"even":{"RB":1},"should":{"MD":2},"new":{"JJ":2},"will":{"MD":1},"much":{"JJ":2,"RB":1},"again":{"RB":1},"negotiation":{"NN":1},"-RSB-":{"-RRB-":1},"not":{"RB":3},"steamships":{"NNS":1},"with":{"IN":6},"from":{"IN":3},"administration":{"NN":3},"dobutful":{"JJ":1},"principal":{"JJ":1},"relations":{"NNS":3},"stopped":{"VBD":1},"acts":{"VBZ":1},"details":{"NNS":1},"bring":{"VB":1},"abrogated":{"VBD":1},"overturn":{"VB":1},"improved":{"VBN":1},"leading":{"VBG":1},"its":{"PRP$":1},"under":{"IN":1},"which":{"WDT":3},"compensation":{"NN":1},"established":{"VBN":1},"brought":{"VBD":1},"courtesy":{"NN":1},"be":{"VB":4},"beneficent":{"JJ":1},"large":{"JJ":1},"into":{"IN":2},"nations":{"NNS":2},"1892":{"CD":1},"competition":{"NN":1},"matter":{"NN":1},"time":{"NN":1},"better":{"JJR":1},"were":{"VBD":5},"America":{"NNP":3},"Central":{"NNP":2},"State":{"NNP":1},"benefit":{"NN":2},"treated":{"VBN":1},"Republicans":{"NNPS":1},"claimed":{"VBN":1},"about":{"RB":1},"many":{"JJ":2},"lines":{"NNS":1},"very":{"RB":1},"we":{"PRP":2},"privilege":{"NN":1},"doubtless":{"JJ":1},"duties":{"NNS":1},"when":{"WRB":1},"policy":{"NN":1},"producers":{"NNS":1},"great":{"JJ":1},"seemed":{"VBD":1},"study":{"NN":1},"other":{"JJ":1},"of":{"IN":27},"summary":{"NN":1},"and":{"CC":19},"undiplomatic":{"JJ":1},"received":{"VBN":1},"predecessor":{"NN":1},"one":{"CD":2},"Southern":{"NNP":1},"increase":{"NN":1},"attracted":{"VBD":1},"desire":{"NN":1},"ever":{"RB":1},"free":{"JJ":2},"cases":{"NNS":1},"the":{"DT":27},"discourtesy":{"NN":1},"those":{"DT":5},"only":{"RB":1}}},"footer":null,"calculatedLanguage":"en"},{"seq":"00000007","version":"b17946956904b0faafc608a1d4059463","tokenCount":488,"lineCount":50,"emptyLineCount":7,"sentenceCount":17,"header":null,"body":{"tokenCount":488,"lineCount":50,"emptyLineCount":7,"sentenceCount":17,"capAlphaSeq":2,"beginCharCount":{"s":3,"y":1,"T":1,"t":9,"J":1,"u":1,"f":1,"a":2,"m":1,"I":2,"i":1,"L":1,"b":2,"l":2,"P":1,"p":4,"0":2,"c":2,"w":3,"O":2,"o":1},"endCharCount":{"e":5,"s":5,"n":1,".":7,"t":3,"f":3,"a":1,"i":1,"-":4,",":2,"g":1,"l":2,"c":1,"h":2,"r":2,"d":3},"tokenPosCount":{"particularly":{"RB":1},"number":{"NN":1},"chief":{"NN":1},"for":{"IN":2},"doubled":{"VBN":1},"Chinese":{"JJ":1},"people":{"NNS":1},"years":{"NNS":1},"this":{"DT":4},"in":{"IN":5},"With":{"IN":1},"your":{"PRP$":1},"are":{"VBP":3},"is":{"VBZ":6},"manufactures":{"VBZ":1},"proportion":{"NN":1},"market":{"NN":1},"difficulty":{"NN":1},"Hawaii":{"NNP":1},"less":{"JJR":2},"system":{"NN":1},"than":{"IN":5},"bulk":{"NN":1},"Democratic":{"JJ":1},"late":{"JJ":1},".":{".":17},"In":{"IN":4},"15":{"CD":1},"whether":{"IN":1},"future":{"NN":1},"industries":{"NNS":1},"Japan":{"NNP":5},"securing":{"VBG":1},"world":{"NN":1},"Trade":{"NNP":1},"Ocean":{"NNP":1,"NN":1},"up":{"RP":1},"seek":{"VB":1},"population":{"NN":1},"war":{"NN":1},"our":{"PRP$":8},"per":{"IN":4},"prevent":{"VB":1},"vast":{"JJ":1},"growth":{"NN":1},"Let":{"VB":1},",000,000,000":{"CD":1},"50":{"CD":1},"present":{"JJ":1},"ready":{"JJ":1},"result":{"NN":1},"outside":{"JJ":1},"just":{"RB":1},"1S93":{"NN":1},"namely":{"RB":1},"us":{"PRP":2},"it":{"PRP":3},"China":{"NNP":6},"two":{"CD":2},"commerce":{"NN":1},"entire":{"JJ":1},"a":{"DT":9},"attention":{"NN":1},"century":{"NN":1},"as":{"IN":1},"ports":{"NNS":2},"exported":{"VBD":2},"has":{"VBZ":3},"she":{"PRP":1},"year":{"NN":3},"10":{"CD":1},"trade":{"NN":10},"coming":{"VBG":1},"wisdom":{"NN":1},"98,000,000":{"CD":1},"desirous":{"JJ":1},"Europe":{"NNP":1},"products":{"NNS":4},"Corea":{"NNP":1},"or":{"CC":5},"tariff":{"NN":1},"tion":{"NN":1},"come":{"VB":1},"21":{"CD":1},"way":{"NN":1},"protective":{"JJ":1},"Canal":{"NNP":1},"i":{"LS":1},"sagacity":{"NN":1},"that":{"IN":2,"WDT":1,"DT":1},"whenever":{"WRB":1},"amount":{"NN":1},",000,000":{"CD":1},"numbers":{"NNS":1},"to":{"TO":11},"took":{"VBD":2},"-":{":":2},"Our":{"PRP$":1},"export":{"NN":1},"fact":{"NN":1},"agriculture":{"NN":1},",":{",":34},"most":{"RBS":1},"these":{"DT":3},"making":{"VBG":1},"situated":{"VBN":1},"there":{"EX":1},"Their":{"PRP$":1},"6":{"CD":1},"000,000":{"CD":2},"addition":{"NN":1},"162,000,000":{"CD":1},"1":{"CD":2},"through":{"IN":1},"depends":{"VBZ":1},"quadrupled":{"VBN":1},"profitable":{"JJ":1},"pacific":{"JJ":1},"The":{"DT":6},"theatre":{"NN":1},"shorter":{"JJR":1},"Australia":{"NNP":1},"on":{"IN":2},"same":{"JJ":3},"legislators":{"NNS":1},"L":{"NN":1},"near":{"JJ":1},"lies":{"VBZ":1},"worth":{"NN":2},"party":{"NN":1},"500,000,000":{"CD":1},"greatest":{"JJS":1},"31":{"CD":1},"imported":{"VBN":1,"VBD":1},"cheaper":{"JJR":1},"nited":{"VBD":1},"1-3":{"CD":1},"everything":{"NN":1},"me":{"PRP":1},"opening":{"NN":1,"VBG":1},"commercial":{"JJ":1},"7,000,000":{"CD":1},"merchants":{"NNS":1},"by":{"IN":1},"should":{"MD":1},"new":{"JJ":1},"will":{"MD":2},"agricultural":{"JJ":1},"foreign":{"JJ":2},"much":{"JJ":1},"little":{"JJ":2},"their":{"PRP$":1},"character":{"NN":1},"with":{"IN":5},"principal":{"JJ":1},"next":{"JJ":1},"energies":{"NNS":1},"relations":{"NNS":2},"furnished":{"VBD":2},"6,000,000":{"CD":1},"done":{"VBN":1},"manufacturers":{"NNS":1},"end":{"NN":1},"thus":{"RB":1},"which":{"WDT":7},"control":{"NN":1},"shall":{"MD":1},"round":{"JJ":1},"ill":{"RB":1},"development":{"NN":1},"be":{"VB":3},"large":{"JJ":1},"into":{"IN":1},"nations":{"NNS":4},"Orient":{"NNP":2},"get":{"VB":1},"route":{"NN":1},"United":{"NNP":3},"her":{"PRP$":1},"Possibilities":{"NNS":1},"Pacific":{"NNP":1},"power":{"NN":1},"more":{"JJR":1,"RBR":1},"destroying":{"VBG":1},"r":{"NN":1},"As":{"IN":1},"Suez":{"NNP":1},"w":{"VBD":1},"cripple":{"VB":1},"$":{"$":9},"call":{"VB":1},"3":{"CD":1},"during":{"IN":1},"amicable":{"JJ":1},"we":{"PRP":3},"Japanese":{"JJ":1},"90,000,000":{"CD":1},"doubtless":{"JJ":3},"value":{"NN":1},"does":{"VBZ":1},"devoted":{"VBN":1},"great":{"JJ":2},"islands":{"NNS":1},"^":{"NN":1},"possible":{"JJ":1},"States":{"NNPS":4},"other":{"JJ":1},"of":{"IN":26},"and":{"CC":17},"one":{"CD":1},"increase":{"VB":1},"free":{"JJ":1},"rapid":{"JJ":1},"28":{"CD":1},"holding":{"VBG":1},"amounts":{"VBZ":1},"the":{"DT":30},"cent":{"NN":4},"only":{"RB":1}}},"footer":null,"calculatedLanguage":"en"},{"seq":"00000008","version":"d636ca1db3e7e9ef420f80ab6ef58bd8","tokenCount":281,"lineCount":28,"emptyLineCount":3,"sentenceCount":8,"header":null,"body":{"tokenCount":281,"lineCount":28,"emptyLineCount":3,"sentenceCount":8,"capAlphaSeq":3,"beginCharCount":{"E":1,"s":2,"T":1,"t":3,"u":1,"U":1,"f":2,"a":1,"m":1,"I":1,"i":2,"l":1,"p":1,"c":1,"W":1,"r":1,"w":2,"o":2},"endCharCount":{"e":4,"s":1,"n":1,"]":3,"y":1,"f":1,"a":1,"-":6,",":1,"g":2,"r":2,"o":2},"tokenPosCount":{"wise":{"JJ":1},"for":{"IN":1},"construction":{"NN":2},"people":{"NNS":5},"reach":{"VB":1},"any":{"DT":1},"impressed":{"JJ":1},"this":{"DT":1},"in":{"IN":2},"With":{"IN":1},"fair":{"JJ":1},"are":{"VBP":4},"is":{"VBZ":3},"firmly":{"RB":1},"equally":{"RB":1},"speedy":{"JJ":1},"proportion":{"NN":1},"system":{"NN":1},"than":{"IN":2},"Empire":{"NNP":1},"This":{"DT":1},".":{".":8},"but":{"CC":1},"2,000":{"CD":1},"giving":{"VBG":1},"sea":{"NN":1},"certainly":{"RB":1},"Japan":{"NNP":1},"proper":{"JJ":1},"substantially":{"RB":1},"project":{"NN":1},"securing":{"VBG":1},"world":{"NN":1},"Yokohama":{"NNP":1},"up":{"RP":1},"so":{"RB":1},"our":{"PRP$":8},"vast":{"JJ":2},"coast":{"NN":1},"do":{"VB":1},"all":{"PDT":2},"miles":{"NNS":1},"necessary":{"JJ":1},"opportunity":{"NN":1},"nearer":{"IN":2},"Great":{"NNP":1},"just":{"RB":1},"lying":{"VBG":1},"China":{"NNP":1},"determined":{"VBN":3},"entire":{"JJ":1},"a":{"DT":3},"Nicaragua":{"NNP":3},"ports":{"NNS":4},"has":{"VBZ":1},"-LSB-":{"-LRB-":3},"Atlantic":{"NNP":1},"trade":{"NN":3},"Europe":{"NNP":1},"or":{"CC":2},"tariff":{"NN":1},"voluntary":{"JJ":1},"applause":{"NN":1},"Applause":{"NN":2},"west":{"NN":1},"they":{"PRP":2},"way":{"NN":1},"growing":{"VBG":1},"protective":{"JJ":1},"open":{"JJ":1},"Canal":{"NNP":3},"citizens":{"NNS":1},"I":{"PRP":1},"borders":{"NNS":1},"whatever":{"WDT":1},"that":{"IN":3,"WDT":1,"DT":2},"out":{"RP":1},"to":{"TO":13},",":{",":10},"share":{"NN":1},";":{":":1},"believe":{"VBP":1},"there":{"EX":1},"hold":{"VB":1},"countries":{"NNS":1},"at":{"IN":1},"through":{"IN":3},"Australia":{"NNP":1},"also":{"RB":1},"markets":{"NNS":1},"on":{"IN":2},"mind":{"NN":1},"my":{"PRP$":1},"take":{"VB":1},"sufficient":{"JJ":1},"itself":{"PRP":1},"York":{"NNP":2},"opening":{"VBG":1},"by":{"IN":1},"either":{"CC":1},"will":{"MD":3},"majority":{"NN":1},"much":{"JJ":1},"-RSB-":{"-RRB-":3},"moment":{"NN":1},"To":{"TO":1},"south":{"NN":1},"earliest":{"JJS":1},"its":{"PRP$":2},"which":{"WDT":1},"control":{"VB":1},"Governmental":{"NNP":1},"shall":{"MD":1},"fully":{"RB":1},"be":{"VB":4},"United":{"NNP":2},"Pacific":{"NNP":1},"Liverpool":{"NNP":1},"European":{"JJ":1},"New":{"NNP":2},"prolonged":{"JJ":1},"American":{"JJ":1},"difference":{"NN":1},"construct":{"VB":1},"canal":{"NN":1},"great":{"JJ":1},"favor":{"NN":2},"thereby":{"RB":1},"action":{"NN":2},"islands":{"NNS":2},"possible":{"JJ":2},"States":{"NNPS":2},"of":{"IN":17},"and":{"CC":11},"one":{"CD":1},"today":{"NN":1},"beyond":{"IN":1},"the":{"DT":25},"maintain":{"VB":1}}},"footer":null,"calculatedLanguage":"en"}]}}